crew.py
crew_utils.py
crew_cli-1.0.0.dist-info/licenses/LICENSE
crew_cli-1.0.0.dist-info/METADATA
crew_cli-1.0.0.dist-info/WHEEL
crew_cli-1.0.0.dist-info/entry_points.txt
crew_cli-1.0.0.dist-info/top_level.txt
crew_cli-1.0.0.dist-info/RECORD
